lmm_tools/__init__.py
lmm_tools/config.py
lmm_tools/data/__init__.py
lmm_tools/data/data.py
lmm_tools/emb/__init__.py
lmm_tools/emb/emb.py
lmm_tools/lmm/__init__.py
lmm_tools/lmm/lmm.py
lmm_tools-0.0.8.dist-info/LICENSE
lmm_tools-0.0.8.dist-info/METADATA
lmm_tools-0.0.8.dist-info/WHEEL
lmm_tools-0.0.8.dist-info/RECORD
